biothings/__init__.py
biothings/__main__.py
biothings/cli/__init__.py
biothings/cli/assistant.py
biothings/cli/dataplugin.py
biothings/cli/exceptions.py
biothings/cli/manager.py
biothings/cli/operations.py
biothings/cli/settings.py
biothings/cli/structure.py
biothings/cli/utils.py
biothings/cli/web_app.py
biothings/cli/templates/README.md
biothings/cli/templates/__init__.py
biothings/cli/templates/manifest.yaml.tpl
biothings/cli/templates/mapping.py
biothings/cli/templates/parallelizer.py
biothings/cli/templates/parser.py
biothings/cli/templates/versions.py
biothings/hub/__init__.py
biothings/hub/default_config.py
biothings/hub/manager.py
biothings/hub/upgrade.py
biothings/hub/api/__init__.py
biothings/hub/api/manager.py
biothings/hub/api/handlers/__init__.py
biothings/hub/api/handlers/base.py
biothings/hub/api/handlers/log.py
biothings/hub/api/handlers/shell.py
biothings/hub/api/handlers/upload.py
biothings/hub/api/handlers/ws.py
biothings/hub/autoupdate/__init__.py
biothings/hub/autoupdate/dumper.py
biothings/hub/autoupdate/uploader.py
biothings/hub/databuild/__init__.py
biothings/hub/databuild/auto_archive.py
biothings/hub/databuild/backend.py
biothings/hub/databuild/buildconfig.py
biothings/hub/databuild/builder.py
biothings/hub/databuild/differ.py
biothings/hub/databuild/mapper.py
biothings/hub/databuild/prebuilder.py
biothings/hub/databuild/syncer.py
biothings/hub/dataexport/__init__.py
biothings/hub/dataexport/ids.py
biothings/hub/dataindex/__init__.py
biothings/hub/dataindex/auto_snapshot_cleanup.py
biothings/hub/dataindex/idcache.py
biothings/hub/dataindex/indexer.py
biothings/hub/dataindex/indexer_cleanup.py
biothings/hub/dataindex/indexer_payload.py
biothings/hub/dataindex/indexer_registrar.py
biothings/hub/dataindex/indexer_schedule.py
biothings/hub/dataindex/indexer_task.py
biothings/hub/dataindex/snapshooter.py
biothings/hub/dataindex/snapshot_cleanup.py
biothings/hub/dataindex/snapshot_registrar.py
biothings/hub/dataindex/snapshot_repo.py
biothings-1.0.2.dist-info/licenses/LICENSE
biothings-1.0.2.dist-info/METADATA
biothings-1.0.2.dist-info/WHEEL
biothings-1.0.2.dist-info/entry_points.txt
biothings-1.0.2.dist-info/top_level.txt
biothings-1.0.2.dist-info/RECORD
