Metadata-Version: 2.4
Name: biothings
Version: 1.0.2
Summary: a toolkit for building high-performance data & knowledge APIs in biology
Author-email: The BioThings Team <dev@biothings.io>
License: Apache-2.0
Project-URL: homepage, https://biothings.io
Project-URL: source, https://github.com/biothings/biothings.api
Project-URL: documentation, https://docs.biothings.io
Project-URL: changelog, https://github.com/biothings/biothings.api/blob/master/CHANGES.txt
Project-URL: issues, https://github.com/biothings/biothings.api/issues
Keywords: biology,medicine,annotation,data,knowledge,web,service,api
Classifier: Programming Language :: Python
Classifier: Programming Language :: Python :: 3
Classifier: Programming Language :: Python :: 3.8
Classifier: Programming Language :: Python :: 3.9
Classifier: Programming Language :: Python :: 3.10
Classifier: Programming Language :: Python :: 3.11
Classifier: Programming Language :: Python :: 3.12
Classifier: Programming Language :: Python :: 3.13
Classifier: Development Status :: 5 - Production/Stable
Classifier: Operating System :: OS Independent
Classifier: Operating System :: POSIX
Classifier: Operating System :: MacOS :: MacOS X
Classifier: Operating System :: Microsoft :: Windows
Classifier: Intended Audience :: Developers
Classifier: Intended Audience :: Science/Research
Classifier: Topic :: Utilities
Classifier: Topic :: Scientific/Engineering :: Bio-Informatics
Classifier: Topic :: Software Development :: Libraries :: Python Modules
Classifier: Topic :: Software Development :: Libraries :: Application Frameworks
Requires-Python: >=3.8
License-File: LICENSE
Requires-Dist: requests>=2.21.0
Requires-Dist: tornado==6.1.0; python_version < "3.7.0"
Requires-Dist: tornado==6.2.0; python_version == "3.7.0"
Requires-Dist: tornado==6.4.2; python_version >= "3.8.0"
Requires-Dist: gitpython>=3.1.0
Requires-Dist: elasticsearch[async]<8,>=7; python_version < "3.7.0"
Requires-Dist: elasticsearch-dsl<8,>=7; python_version < "3.7.0"
Requires-Dist: elasticsearch[async]<9,>=8; python_version >= "3.7.0"
Requires-Dist: elasticsearch-dsl<9,>=8; python_version >= "3.7.0"
Requires-Dist: singledispatchmethod; python_version < "3.8.0"
Requires-Dist: dataclasses; python_version < "3.7.0"
Requires-Dist: jmespath<2.0.0,>=0.7.1
Requires-Dist: PyYAML>=5.1
Requires-Dist: orjson>=3.6.1
Provides-Extra: web-extra
Requires-Dist: msgpack>=0.6.1; extra == "web-extra"
Requires-Dist: sentry-sdk>=1.5.3; extra == "web-extra"
Provides-Extra: opensearch
Requires-Dist: boto3; extra == "opensearch"
Requires-Dist: requests-aws4auth; extra == "opensearch"
Provides-Extra: hubcore
Requires-Dist: pymongo<5.0,>=4.1.0; extra == "hubcore"
Provides-Extra: hub
Requires-Dist: pymongo<5.0,>=4.1.0; extra == "hub"
Requires-Dist: beautifulsoup4; extra == "hub"
Requires-Dist: aiocron==1.8; extra == "hub"
Requires-Dist: asyncssh>=2.19.0; extra == "hub"
Requires-Dist: psutil; extra == "hub"
Requires-Dist: jsonpointer; extra == "hub"
Requires-Dist: IPython; extra == "hub"
Requires-Dist: multiprocessing_on_dill; extra == "hub"
Requires-Dist: dill; extra == "hub"
Requires-Dist: prettytable; extra == "hub"
Requires-Dist: sockjs-tornado==1.0.7; extra == "hub"
Requires-Dist: jsonschema>=2.6.0; extra == "hub"
Requires-Dist: pip; extra == "hub"
Requires-Dist: black; extra == "hub"
Requires-Dist: boto3; extra == "hub"
Requires-Dist: requests-aws4auth; extra == "hub"
Requires-Dist: networkx<3.0,>=2.1; python_version >= "3.7.0" and extra == "hub"
Requires-Dist: networkx<2.6,>=2.1; python_version < "3.7.0" and extra == "hub"
Requires-Dist: biothings_client>=0.2.6; extra == "hub"
Requires-Dist: cryptography>=38.0.3; extra == "hub"
Requires-Dist: pytest; extra == "hub"
Requires-Dist: pydantic>=2.0; extra == "hub"
Provides-Extra: cli
Requires-Dist: pymongo<5.0,>=4.1.0; extra == "cli"
Requires-Dist: psutil; extra == "cli"
Requires-Dist: jsonschema>=2.6.0; extra == "cli"
Requires-Dist: typer>=0.12.1; extra == "cli"
Provides-Extra: docker
Requires-Dist: docker>=6.0.1; extra == "docker"
Provides-Extra: docker-ssh
Requires-Dist: docker[ssh]>=6.0.1; extra == "docker-ssh"
Provides-Extra: dev
Requires-Dist: aioresponses; extra == "dev"
Requires-Dist: mongomock; extra == "dev"
Requires-Dist: pytest-asyncio; extra == "dev"
Requires-Dist: pytest-mock; extra == "dev"
Provides-Extra: docs
Requires-Dist: sphinx>=5.3.0; extra == "docs"
Requires-Dist: sphinx_rtd_theme>=2.0.0; extra == "docs"
Requires-Dist: sphinx_reredirects>=0.1.3; extra == "docs"
Dynamic: license-file
